shuft/__init__.py
shuft/__main__.py
shuft/shuft.py
shuft-1.1.1.dist-info/LICENSE
shuft-1.1.1.dist-info/METADATA
shuft-1.1.1.dist-info/WHEEL
shuft-1.1.1.dist-info/entry_points.txt
shuft-1.1.1.dist-info/top_level.txt
shuft-1.1.1.dist-info/RECORD
