Metadata-Version: 2.1
Name: shuft
Version: 1.1.1
Summary: Tool for uploading folders and files via sftp.
Home-page: https://github.com/steinwurf/shuft
Author: Steinwurf ApS
Author-email: contact@steinwurf.com
License: BSD 3-clause "New" or "Revised" License
Keywords: sftp
Platform: UNKNOWN
Classifier: Development Status :: 5 - Production/Stable
Classifier: Intended Audience :: Developers
Classifier: License :: OSI Approved :: BSD License
Classifier: Operating System :: OS Independent
Classifier: Programming Language :: Python :: 3.5
Classifier: Programming Language :: Python :: 3.6
Classifier: Programming Language :: Python :: 3.7
Classifier: Topic :: Internet :: File Transfer Protocol (FTP)
Classifier: Topic :: Utilities
Requires-Dist: asyncssh
